abakus/__init__.py
abakus/auth.py
abakus/utils.py
django_auth_abakus-1.1.0.dist-info/DESCRIPTION.rst
django_auth_abakus-1.1.0.dist-info/METADATA
django_auth_abakus-1.1.0.dist-info/metadata.json
django_auth_abakus-1.1.0.dist-info/RECORD
django_auth_abakus-1.1.0.dist-info/top_level.txt
django_auth_abakus-1.1.0.dist-info/WHEEL
tests/__init__.py
tests/local.py
tests/models.py
tests/settings.py
tests/tests.py
tests/urls.py
