Metadata-Version: 2.0
Name: django-auth-abakus
Version: 1.1.0
Summary: A django auth module that can be used to to authenticate users against the API of abakus.no.
Home-page: http://github.com/webkom/django-auth-abakus
Author: Webkom, Abakus Linjeforening
Author-email: webkom@abakus.no
License: MIT
Platform: UNKNOWN
Classifier: Programming Language :: Python
Classifier: Programming Language :: Python :: 2.7
Classifier: Programming Language :: Python :: 3.3
Classifier: Programming Language :: Python :: 3.4
Classifier: Topic :: Software Development :: Libraries :: Python Modules
Classifier: Framework :: Django
Classifier: Environment :: Web Environment
Classifier: Operating System :: OS Independent
Classifier: Natural Language :: English
Requires-Dist: requests (==2.4.3)
